teedoc_plugin_ad_hint/__init__.py
teedoc_plugin_ad_hint/assets/main.js
teedoc_plugin_ad_hint/assets/style.css
teedoc_plugin_ad_hint-1.1.3.dist-info/LICENSE
teedoc_plugin_ad_hint-1.1.3.dist-info/METADATA
teedoc_plugin_ad_hint-1.1.3.dist-info/WHEEL
teedoc_plugin_ad_hint-1.1.3.dist-info/top_level.txt
teedoc_plugin_ad_hint-1.1.3.dist-info/RECORD
