Metadata-Version: 2.1
Name: teedoc-plugin-ad-hint
Version: 1.1.3
Summary: advertisement and hint plugin for teedoc
Home-page: https://github.com/Neutree/teedoc
Author: Neucrack
Author-email: CZD666666@gmail.com
License: MIT
Keywords: advertisement hint teedoc plugin
Platform: UNKNOWN
Classifier: Intended Audience :: Developers
Classifier: License :: OSI Approved :: MIT License
Classifier: Programming Language :: Python :: 3
